CLASSIFIERS
LICENSE.txt
MANIFEST.in
README.rst
setup.py
versioneer.py
mock_matchers/__init__.py
mock_matchers/_version.py
mock_matchers/version.py
mock_matchers.egg-info/PKG-INFO
mock_matchers.egg-info/SOURCES.txt
mock_matchers.egg-info/dependency_links.txt
mock_matchers.egg-info/not-zip-safe
mock_matchers.egg-info/requires.txt
mock_matchers.egg-info/top_level.txt
requirements/main.txt