Metadata-Version: 1.1
Name: mock-matchers
Version: 0.0.1
Summary: hamcrest matchers for mock assertions
Home-page: https://github.com/alisaifee/mock-matchers
Author: Ali-Akber Saifee
Author-email: ali@indydevs.org
License: Copyright (c) 2014 Ali-Akber Saifee 
